correos_preregistro/__init__.py
correos_preregistro/client.py
correos_preregistro/errors.py
correos_preregistro/vars.py
correos_preregistro/requests/__init__.py
correos_preregistro/requests/preregistro_envio.py
correos_preregistro/resources/__init__.py
correos_preregistro/resources/package.py
correos_preregistro/resources/receiver.py
correos_preregistro/resources/sender.py
correos_preregistro/responses/__init__.py
correos_preregistro/responses/preregistro_envio.py
correos_preregistro/services/__init__.py
correos_preregistro/services/shipment.py
correos_preregistro-0.0.6.dist-info/METADATA
correos_preregistro-0.0.6.dist-info/WHEEL
correos_preregistro-0.0.6.dist-info/top_level.txt
correos_preregistro-0.0.6.dist-info/RECORD
