Metadata-Version: 2.1
Name: correos-preregistro
Version: 0.0.6
Summary: Python wrapper for Correos PreRegistro SOAP API
Home-page: https://git.coopdevs.org/coopdevs/som-connexio/correos/correos-preregistro
Author: Coopdevs, Som Connexio
Author-email: info@coopdevs.org
Maintainer: Daniel Palomar, Gerard Funosas
License: UNKNOWN
Platform: UNKNOWN
Classifier: Development Status :: 3 - Alpha
Classifier: Operating System :: POSIX :: Linux
Classifier: Programming Language :: Python :: 2
Classifier: Programming Language :: Python :: 2.7
Requires-Dist: requests (==2.28.1)
Requires-Dist: lxml (==4.9.2)
Requires-Dist: zeep (==4.2.1)
